LICENSE
README.md
setup.py
poptus.egg-info/PKG-INFO
poptus.egg-info/SOURCES.txt
poptus.egg-info/dependency_links.txt
poptus.egg-info/requires.txt
poptus.egg-info/top_level.txt
pounders/__init__.py